search_forecast/__init__.py
search_forecast/_modidx.py
search_forecast/model/__init__.py
search_forecast/model/search_volume.py
search_forecast/utils/__init__.py
search_forecast/utils/data_gen.py
search_forecast/wrapper/__init__.py
search_forecast/wrapper/pymc_wrapper.py
search_forecast-0.0.1.dist-info/licenses/LICENSE
search_forecast-0.0.1.dist-info/METADATA
search_forecast-0.0.1.dist-info/WHEEL
search_forecast-0.0.1.dist-info/entry_points.txt
search_forecast-0.0.1.dist-info/top_level.txt
search_forecast-0.0.1.dist-info/RECORD
