Metadata-Version: 2.4
Name: search-forecast
Version: 0.0.1
Summary: Search forecasting tool
Home-page: https://github.com/redam94/search-forecast
Author: Matthew Reda
Author-email: m.reda94@gmail.com
License: Apache Software License 2.0
Keywords: nbdev jupyter notebook python
Classifier: Development Status :: 4 - Beta
Classifier: Intended Audience :: Developers
Classifier: Natural Language :: English
Classifier: Programming Language :: Python :: 3.10
Classifier: Programming Language :: Python :: 3.11
Classifier: Programming Language :: Python :: 3.12
Classifier: License :: OSI Approved :: Apache Software License
Requires-Python: >=3.10
License-File: LICENSE
Requires-Dist: pymc
Requires-Dist: jax
Requires-Dist: numba
Requires-Dist: numpyro
Requires-Dist: nutpie
Requires-Dist: pandas
Requires-Dist: numpy
Requires-Dist: dowhy
Requires-Dist: pymc-marketing
Requires-Dist: tensorflow_probability
Requires-Dist: tueplots
Requires-Dist: plotly
Provides-Extra: dev
Dynamic: author
Dynamic: author-email
Dynamic: classifier
Dynamic: description
Dynamic: description-content-type
Dynamic: home-page
Dynamic: keywords
Dynamic: license
Dynamic: license-file
Dynamic: provides-extra
Dynamic: requires-dist
Dynamic: requires-python
Dynamic: summary
